{
  "routes": [
    {
      "method": "GET",
      "path": "/position",
      "handler": "Position.find",
      "config": {
        "policies": []
      }
    },
    {
      "method": "GET",
      "path": "/position/count",
      "handler": "Position.count",
      "config": {
        "policies": []
      }
    },
    {
      "method": "GET",
      "path": "/position/:_id",
      "handler": "Position.findOne",
      "config": {
        "policies": []
      }
    },
    {
      "method": "POST",
      "path": "/position",
      "handler": "Position.create",
      "config": {
        "policies": []
      }
    },
    {
      "method": "PUT",
      "path": "/position/:_id",
      "handler": "Position.update",
      "config": {
        "policies": []
      }
    },
    {
      "method": "DELETE",
      "path": "/position/:_id",
      "handler": "Position.destroy",
      "config": {
        "policies": []
      }
    }
  ]
}
